crudgen_django/__init__.py
crudgen_django/apps.py
crudgen_django/console/__init__.py
crudgen_django/console/generate.py
crudgen_django/endpoints.py
crudgen_django/fields.py
crudgen_django/hacks/configs.py
crudgen_django/models.py
crudgen_django/serializers.py
crudgen_django/services.py
crudgen_django-0.1.5.dist-info/entry_points.txt
crudgen_django-0.1.5.dist-info/LICENSE
crudgen_django-0.1.5.dist-info/WHEEL
crudgen_django-0.1.5.dist-info/METADATA
crudgen_django-0.1.5.dist-info/RECORD
